pyx2py-0.1.0.data/scripts/pyx2py
pyx2py-0.1.0.dist-info/DESCRIPTION.rst
pyx2py-0.1.0.dist-info/METADATA
pyx2py-0.1.0.dist-info/RECORD
pyx2py-0.1.0.dist-info/WHEEL
pyx2py-0.1.0.dist-info/metadata.json
pyx2py-0.1.0.dist-info/top_level.txt
tests/__init__.py
tests/test_sample.py
